arcane/date.py
rcane_date-0.1.2.dist-info/WHEEL
rcane_date-0.1.2.dist-info/METADATA
rcane_date-0.1.2.dist-info/RECORD
