Metadata-Version: 2.1
Name: rcane-date
Version: 0.1.2
Summary: A package to work with dates
Author: Arcane
Author-email: product@arcane.run
Requires-Python: >=3.6,<4.0
Classifier: Programming Language :: Python :: 3
Classifier: Programming Language :: Python :: 3.10
Classifier: Programming Language :: Python :: 3.6
Classifier: Programming Language :: Python :: 3.7
Classifier: Programming Language :: Python :: 3.8
Classifier: Programming Language :: Python :: 3.9
